channels_rest_framework/__init__.py
channels_rest_framework/consumers.py
channels_rest_framework/decorators.py
channels_rest_framework/exceptions.py
channels_rest_framework/generics.py
channels_rest_framework/handlers.py
channels_rest_framework/mixins.py
channels_rest_framework/permissions.py
channels_rest_framework/routings.py
channels_rest_framework/utils.py
rest_framework_channels/__init__.py
rest_framework_channels/consumers.py
rest_framework_channels/decorators.py
rest_framework_channels/exceptions.py
rest_framework_channels/generics.py
rest_framework_channels/handlers.py
rest_framework_channels/mixins.py
rest_framework_channels/permissions.py
rest_framework_channels/routings.py
rest_framework_channels/settings.py
rest_framework_channels/utils.py
rest_framework_channels/testing/__init__.py
rest_framework_channels/testing/websocket.py
rest_framework_channels-0.0.6.dist-info/LICENSE
rest_framework_channels-0.0.6.dist-info/METADATA
rest_framework_channels-0.0.6.dist-info/WHEEL
rest_framework_channels-0.0.6.dist-info/top_level.txt
rest_framework_channels-0.0.6.dist-info/RECORD
