Metadata-Version: 2.1
Name: rest-framework-channels
Version: 0.0.6
Summary: Brings async, event-driven capabilities to Django.
Home-page: https://github.com/jjjkkkjjj/rest_framework_channels
Author: jjjkkkjjj
Author-email: junnosuke.kado.git@gmail.com
License: MIT
Platform: UNKNOWN
Classifier: Development Status :: 5 - Production/Stable
Classifier: Environment :: Web Environment
Classifier: Intended Audience :: Developers
Classifier: License :: OSI Approved :: MIT License
Classifier: Operating System :: OS Independent
Classifier: Programming Language :: Python
Classifier: Programming Language :: Python :: 3
Classifier: Programming Language :: Python :: 3.8
Classifier: Programming Language :: Python :: 3.9
Classifier: Programming Language :: Python :: 3.10
Classifier: Programming Language :: Python :: 3.11
Classifier: Programming Language :: Python :: 3.12
Classifier: Framework :: Django
Classifier: Framework :: Django :: 4.2
Classifier: Framework :: Django :: 5.0
Classifier: Framework :: Django :: 5.1
Classifier: Topic :: Internet :: WWW/HTTP
Requires-Python: >=3.8
License-File: LICENSE
Requires-Dist: Django (>=4.2)
Requires-Dist: channels (>=4.0.0)
Requires-Dist: asgiref (<4,>=3.6.0)
Requires-Dist: djangorestframework
Provides-Extra: daphne
Requires-Dist: daphne (>=4.0.0) ; extra == 'daphne'
Provides-Extra: tests
Requires-Dist: async-timeout ; extra == 'tests'
Requires-Dist: coverage (>=6.3.1) ; extra == 'tests'
Requires-Dist: pytest (>=7.0.1) ; extra == 'tests'
Requires-Dist: pytest-django (>=4.5.2) ; extra == 'tests'
Requires-Dist: pytest-asyncio (>=0.18.1) ; extra == 'tests'
